Metadata-Version: 1.1
Name: pyboiler
Version: 0.3.0
Summary: Creates a configurable python project template in a given directory.
Home-page: https://pypi.python.org/pypi/pyboiler
Author: Link-
Author-email: bsm.dgdy@gmail.com
License: LICENSE
Keywords: boilerplate python script configurable
Platform: UNKNOWN
Classifier: Intended Audience :: Developers
Classifier: Development Status :: 3 - Alpha
Classifier: Programming Language :: Python :: 2.7
Classifier: Topic :: Software Development :: Build Tools
